README.md
setup.py
parler/__init__.py
parler.egg-info/PKG-INFO
parler.egg-info/SOURCES.txt
parler.egg-info/dependency_links.txt
parler.egg-info/requires.txt
parler.egg-info/top_level.txt