Metadata-Version: 2.1
Name: parler
Version: 1.0.1
Summary: Parler Social Media Python API SDK
Home-page: https://gitlab.com/coffeemaninc/parler-api/
Author: Caffman
Author-email: caff@none.com
License: MIT
Platform: UNKNOWN
Requires-Python: >=3.6
